platform_location_shared/__init__.py
platform_location_shared/models/__init__.py
platform_location_shared/models/error.py
platform_location_shared/models/location.py
platform_location_shared/models/mixins/__init__.py
platform_location_shared/models/mixins/serialise.py
platform_location_shared/validations/__init__.py
platform_location_shared/validations/postcode.py
platform_location_shared-0.6.0.dist-info/METADATA
platform_location_shared-0.6.0.dist-info/WHEEL
platform_location_shared-0.6.0.dist-info/RECORD
